net_utils_ky/__init__.py
net_utils_ky/async_utils.py
net_utils_ky/cli.py
net_utils_ky/core.py
net_utils_ky/exceptions.py
net_utils_ky/kyanos_entry.py
net_utils_ky/libs/code
net_utils_ky-0.3.1.dist-info/licenses/LICENSE
tests/__init__.py
tests/test_core.py
net_utils_ky-0.3.1.dist-info/METADATA
net_utils_ky-0.3.1.dist-info/WHEEL
net_utils_ky-0.3.1.dist-info/entry_points.txt
net_utils_ky-0.3.1.dist-info/top_level.txt
net_utils_ky-0.3.1.dist-info/RECORD
